JinxxObbSearch/__init__.py
JinxxObbSearch/search.py
JinxxObbSearch-0.1.8.dist-info/METADATA
JinxxObbSearch-0.1.8.dist-info/WHEEL
JinxxObbSearch-0.1.8.dist-info/entry_points.txt
JinxxObbSearch-0.1.8.dist-info/top_level.txt
JinxxObbSearch-0.1.8.dist-info/RECORD
