Metadata-Version: 2.1
Name: JinxxObbSearch
Version: 0.1.8
Requires-Dist: tqdm ==4.66.1
